mili/__init__.py
mili/__main__.py
mili/_core.py
mili/_coreutils.py
mili/_richtext.py
mili/animation.py
mili/data.py
mili/error.py
mili/icon.py
mili/mili.py
mili/style.py
mili/typing.py
mili/utility.py
mili/_utils/_context_menu.py
mili/_utils/_entries.py
mili/_utils/_interaction.py
mili/_utils/_prefabs.py
mili/_utils/_window.py
mili/demo/demo.py
mili_ui-1.0.7.dist-info/licenses/LICENSE.txt
mili_ui-1.0.7.dist-info/METADATA
mili_ui-1.0.7.dist-info/WHEEL
mili_ui-1.0.7.dist-info/entry_points.txt
mili_ui-1.0.7.dist-info/top_level.txt
mili_ui-1.0.7.dist-info/RECORD
