Metadata-Version: 2.4
Name: mili-ui
Version: 1.0.7
Summary: Minimal immediate-mode python user interface library
Author: damusss
License: Copyright (c) 2024 https://github.com/damusss
Project-URL: Homepage, https://github.com/damusss/mili
Project-URL: Issues, https://github.com/damusss/mili/issues
Project-URL: Documentation, https://github.com/damusss/mili/blob/main/guide/guide.md
Keywords: gui,ui,pygame,pygame-ce
Classifier: Programming Language :: Python :: 3
Classifier: License :: OSI Approved :: MIT License
Classifier: Operating System :: OS Independent
Requires-Python: >=3.12
License-File: LICENSE.txt
Requires-Dist: pygame-ce>=2.5.2
Dynamic: license-file
